cisco_acl/__init__.py
cisco_acl/ace.py
cisco_acl/ace_base.py
cisco_acl/ace_group.py
cisco_acl/acl.py
cisco_acl/addr_group.py
cisco_acl/address.py
cisco_acl/address_ag.py
cisco_acl/address_base.py
cisco_acl/base.py
cisco_acl/config_parser.py
cisco_acl/functions.py
cisco_acl/group.py
cisco_acl/helpers.py
cisco_acl/option.py
cisco_acl/parsers.py
cisco_acl/port.py
cisco_acl/port_name.py
cisco_acl/protocol.py
cisco_acl/py.typed
cisco_acl/remark.py
cisco_acl/types_.py
cisco_acl/wildcard.py
cisco_acl-3.2.1.dist-info/METADATA
cisco_acl-3.2.1.dist-info/WHEEL
cisco_acl-3.2.1.dist-info/RECORD
