Metadata-Version: 2.1
Name: cisco_acl
Version: 3.2.1
Summary: Python package to parse and manage Cisco ACL (Access Control List)
Home-page: https://github.com/vladimirs-git/cisco-acl
License: Apache-2.0
Keywords: cisco,acl,ios,nexus,nx-os
Author: Vladimirs Prusakovs
Author-email: vladimir.prusakovs@gmail.com
Requires-Python: >=3.8,<4.0
Classifier: Development Status :: 5 - Production/Stable
Classifier: Intended Audience :: Developers
Classifier: License :: OSI Approved :: Apache Software License
Classifier: Natural Language :: English
Classifier: Programming Language :: Python :: 3
Classifier: Programming Language :: Python :: 3.8
Classifier: Programming Language :: Python :: 3.9
Classifier: Programming Language :: Python :: 3.10
Classifier: Programming Language :: Python :: 3.11
Classifier: Topic :: System :: Networking
Provides-Extra: test
Requires-Dist: netports (>=0.12.1,<0.13.0)
Project-URL: Bug Tracker, https://github.com/vladimirs-git/cisco-acl/issues
Project-URL: Download URL, https://github.com/vladimirs-git/cisco-acl/archive/refs/tags/3.2.1.tar.gz
Project-URL: Repository, https://github.com/vladimirs-git/cisco-acl
